<?xml version="1.0" ?>
<model xmlns="http://namespaces.plone.org/supermodel/schema">
    
    <!-- This model is loaded at startup and used to populate the IPage
         interface in page.py.
      -->
    
    <schema>
        <field name="title" type="zope.schema.TextLine">
            <title>Page title</title>
            <description>A short and punchy title</description>
            <required>True</required>
        </field>
        <field name="description" type="zope.schema.Text">
            <title>Description</title>
            <description>Short summary</description>
            <required>False</required>
        </field>
        <field name="body" type="zope.schema.Text">
            <title>Body text</title>
            <description>Body text for the page</description>
            <required>True</required>
        </field>
    </schema>
    
</model>